[
    {
        "id": "16300914781440.8952241207458901",
        "nome": "Izabella",
        "email": "iza@gmail.com",
        "data_nasc": "1991/11/08",
        "class_id":"16300914781440.8952241207458947"
    },
    {
        "id": "16300914781440.8952241207458109",
        "nome": "Vitoria",
        "email": "vi@gmail.com",
        "data_nasc": "2001/01/01",
        "class_id":"16300911961130.023888981972295389"
    },
    {
        "id": "16300914781440.8952241207458789",
        "nome": "Thais",
        "email": "Thais@gmail.com",
        "data_nasc": "1991/01/01",
        "class_id":"diponivel"
    }
]